airflow/providers/apache/beam/README.md
airflow/providers/apache/beam/__init__.py
airflow/providers/apache/beam/get_provider_info.py
airflow/providers/apache/beam/version_compat.py
airflow/providers/apache/beam/hooks/__init__.py
airflow/providers/apache/beam/hooks/beam.py
airflow/providers/apache/beam/operators/__init__.py
airflow/providers/apache/beam/operators/beam.py
airflow/providers/apache/beam/triggers/__init__.py
airflow/providers/apache/beam/triggers/beam.py
apache_airflow_providers_apache_beam-6.2.2.dist-info/entry_points.txt
apache_airflow_providers_apache_beam-6.2.2.dist-info/licenses/LICENSE
apache_airflow_providers_apache_beam-6.2.2.dist-info/licenses/NOTICE
apache_airflow_providers_apache_beam-6.2.2.dist-info/WHEEL
apache_airflow_providers_apache_beam-6.2.2.dist-info/METADATA
apache_airflow_providers_apache_beam-6.2.2.dist-info/RECORD
