Metadata-Version: 2.4
Name: apache-airflow-providers-apache-beam
Version: 6.2.2
Summary: Provider package apache-airflow-providers-apache-beam for Apache Airflow
Keywords: airflow-provider,apache.beam,airflow,integration
Author-email: Apache Software Foundation <dev@airflow.apache.org>
Maintainer-email: Apache Software Foundation <dev@airflow.apache.org>
Requires-Python: >=3.10,!=3.13
License-Expression: Apache-2.0
Classifier: Development Status :: 5 - Production/Stable
Classifier: Environment :: Console
Classifier: Environment :: Web Environment
Classifier: Intended Audience :: Developers
Classifier: Intended Audience :: System Administrators
Classifier: Framework :: Apache Airflow
Classifier: Framework :: Apache Airflow :: Provider
Classifier: Programming Language :: Python :: 3.10
Classifier: Programming Language :: Python :: 3.11
Classifier: Programming Language :: Python :: 3.12
Classifier: Topic :: System :: Monitoring
License-File: LICENSE
License-File: NOTICE
Requires-Dist: apache-airflow>=2.11.0
Requires-Dist: apache-airflow-providers-common-compat>=1.12.0
Requires-Dist: apache-beam>=2.60.0; python_version < "3.13"
Requires-Dist: pyarrow>=16.1.0; python_version < '3.13'
Requires-Dist: numpy>=1.22.4; python_version<'3.11'
Requires-Dist: numpy>=1.23.2; python_version<'3.12' and python_version>='3.11'
Requires-Dist: numpy>=1.26.0; python_version>='3.12' and python_version < '3.13'
Requires-Dist: apache-beam[gcp]>=2.60.0 ; extra == "google" and ( python_version < "3.13")
Project-URL: Bug Tracker, https://github.com/apache/airflow/issues
Project-URL: Changelog, https://airflow.apache.org/docs/apache-airflow-providers-apache-beam/6.2.2/changelog.html
Project-URL: Documentation, https://airflow.apache.org/docs/apache-airflow-providers-apache-beam/6.2.2
Project-URL: Mastodon, https://fosstodon.org/@airflow
Project-URL: Slack Chat, https://s.apache.org/airflow-slack
Project-URL: Source Code, https://github.com/apache/airflow
Project-URL: YouTube, https://www.youtube.com/channel/UCSXwxpWZQ7XZ1WL3wqevChA/
Provides-Extra: google
